Metadata-Version: 2.1
Name: mctlib
Version: 0.0.2
Summary: some extra functions
Home-page: 
Author: Mate Chocheli
Author-email: matechocheli2@gmail.com
License: MIT
Keywords: mistacheeselib
Classifier: Development Status :: 5 - Production/Stable
Classifier: Intended Audience :: Education
Classifier: Operating System :: OS Independent
Classifier: License :: OSI Approved :: MIT License
Classifier: Programming Language :: Python :: 3
License-File: LICENSE.txt
